tap_shortcut/__init__.py
tap_shortcut/__main__.py
tap_shortcut/client.py
tap_shortcut/openapi.json
tap_shortcut/streams.py
tap_shortcut/tap.py
tap_shortcut-0.7.3.dist-info/METADATA
tap_shortcut-0.7.3.dist-info/WHEEL
tap_shortcut-0.7.3.dist-info/entry_points.txt
tap_shortcut-0.7.3.dist-info/licenses/LICENSE
tap_shortcut-0.7.3.dist-info/RECORD
