Metadata-Version: 2.4
Name: tap-shortcut
Version: 0.7.3
Summary: Singer tap for Shortcut, built with the Meltano SDK for Singer Taps.
Project-URL: Documentation, https://github.com/reservoir-data/tap-shortcut#readme
Project-URL: Homepage, https://github.com/reservoir-data/tap-shortcut
Project-URL: Repository, https://github.com/reservoir-data/tap-shortcut
Author-email: Edgar Ramírez-Mondragón <edgarrm358@gmail.com>
Maintainer-email: Edgar Ramírez-Mondragón <edgarrm358@gmail.com>
License-Expression: Apache-2.0
License-File: LICENSE
Keywords: ELT,Shortcut,singer.io
Classifier: Programming Language :: Python :: 3 :: Only
Classifier: Programming Language :: Python :: 3.10
Classifier: Programming Language :: Python :: 3.11
Classifier: Programming Language :: Python :: 3.12
Classifier: Programming Language :: Python :: 3.13
Classifier: Programming Language :: Python :: 3.14
Requires-Python: >=3.10
Requires-Dist: requests
Requires-Dist: singer-sdk~=0.52.5
Requires-Dist: toolz==1.1
Requires-Dist: typing-extensions>=4.14; python_full_version < '3.12'
